ansible_toolkit/__init__.py
ansible_toolkit/dao.py
ansible_toolkit/exceptions.py
ansible_toolkit/git_diff.py
ansible_toolkit/show_template.py
ansible_toolkit/show_vars.py
ansible_toolkit/utils.py
ansible_toolkit/utils_ansible.py
ansible_toolkit/vault.py
ansible_toolkit_ng-2.0.0.data/scripts/atk-git-diff
ansible_toolkit_ng-2.0.0.data/scripts/atk-show-template
ansible_toolkit_ng-2.0.0.data/scripts/atk-show-vars
ansible_toolkit_ng-2.0.0.data/scripts/atk-vault
ansible_toolkit_ng-2.0.0.dist-info/LICENSE.txt
ansible_toolkit_ng-2.0.0.dist-info/METADATA
ansible_toolkit_ng-2.0.0.dist-info/WHEEL
ansible_toolkit_ng-2.0.0.dist-info/top_level.txt
ansible_toolkit_ng-2.0.0.dist-info/RECORD
