Metadata-Version: 2.1
Name: ansible-toolkit-ng
Version: 2.0.0
Summary: The missing Ansible tools
Home-page: http://github.com/sorrowless/ansible-toolkit-ng
Author: Stan Bogatkin
Author-email: stabog.tmb@gmail.com
License: GPLv3
Platform: UNKNOWN
Requires-Dist: ansible
